task2/counter.sv
module counter #(
    parameter WIDTH = 16
)(
    // interface signals
    input logic clk, // clock
    input logic rst, //reset
    input logic en, //counter enable
    output logic [WIDTH-1:0] count //count output
);

always_ff @ (posedge clk) //positive edge clock
    if (rst) count <= {WIDTH{1'b0}};
    else count <= count + (en ? {{WIDTH-1{1'b0}},1'b1} : {WIDTH{1'b1}});//{{WIDTH-1{1'b0}},en}; //clock addition

endmodule

task2/counter.vcd
$version Generated by VerilatedVcd $end
$date Mon Nov  7 02:43:57 2022 $end
$timescale 1ps $end

 $scope module TOP $end
  $var wire  1 # clk $end
  $var wire 16 & count [15:0] $end
  $var wire  1 % en $end
  $var wire  1 $ rst $end
  $scope module counter $end
   $var wire 32 ' WIDTH [31:0] $end
   $var wire  1 # clk $end
   $var wire 16 & count [15:0] $end
   $var wire  1 % en $end
   $var wire  1 $ rst $end
  $upscope $end
 $upscope $end
$enddefinitions $end


#0
1#
1$
0%
b0000000000000000 &
b00000000000000000000000000010000 '
#1
0#
#2
1#
#3
0#
#4
1#
#5
0#
#6
1#
0$
#7
0#
#8
1#
b1111111111111111 &
#9
0#
#10
1#
b1111111111111110 &
#11
0#
#12
1#
b1111111111111101 &
#13
0#
#14
1#
b1111111111111100 &
#15
0#
#16
1#
b1111111111111011 &
#17
0#
#18
1#
b1111111111111010 &
#19
0#
#20
1#
b1111111111111001 &
#21
0#
#22
1#
b1111111111111000 &
#23
0#
#24
1#
b1111111111110111 &
#25
0#
#26
1#
b1111111111110110 &
#27
0#
#28
1#
1$
b1111111111110101 &
#29
0#
#30
1#
0$
b0000000000000000 &
#31
0#
#32
1#
b1111111111111111 &
#33
0#
#34
1#
b1111111111111110 &
#35
0#
#36
1#
b1111111111111101 &
#37
0#
#38
1#
b1111111111111100 &
#39
0#
#40
1#
b1111111111111011 &
#41
0#
#42
1#
b1111111111111010 &
#43
0#
#44
1#
b1111111111111001 &
#45
0#
#46
1#
b1111111111111000 &
#47
0#
#48
1#
b1111111111110111 &
#49
0#
#50
1#
b1111111111110110 &
#51
0#
#52
1#
b1111111111110101 &
#53
0#
#54
1#
b1111111111110100 &
#55
0#
#56
1#
b1111111111110011 &
#57
0#
#58
1#
b1111111111110010 &
#59
0#
#60
1#
b1111111111110001 &
#61
0#
#62
1#
b1111111111110000 &
#63
0#
#64
1#
b1111111111101111 &
#65
0#
#66
1#
b1111111111101110 &
#67
0#
#68
1#
b1111111111101101 &
#69
0#
#70
1#
b1111111111101100 &
#71
0#
#72
1#
b1111111111101011 &
#73
0#
#74
1#
b1111111111101010 &
#75
0#
#76
1#
b1111111111101001 &
#77
0#
#78
1#
b1111111111101000 &
#79
0#
#80
1#
b1111111111100111 &
#81
0#
#82
1#
b1111111111100110 &
#83
0#
#84
1#
b1111111111100101 &
#85
0#
#86
1#
b1111111111100100 &
#87
0#
#88
1#
b1111111111100011 &
#89
0#
#90
1#
b1111111111100010 &
#91
0#
#92
1#
b1111111111100001 &
#93
0#
#94
1#
b1111111111100000 &
#95
0#
#96
1#
b1111111111011111 &
#97
0#
#98
1#
b1111111111011110 &
#99
0#
#100
1#
b1111111111011101 &
#101
0#
#102
1#
b1111111111011100 &
#103
0#
#104
1#
b1111111111011011 &
#105
0#
#106
1#
b1111111111011010 &
#107
0#
#108
1#
b1111111111011001 &
#109
0#
#110
1#
b1111111111011000 &
#111
0#
#112
1#
b1111111111010111 &
#113
0#
#114
1#
b1111111111010110 &
#115
0#
#116
1#
b1111111111010101 &
#117
0#
#118
1#
b1111111111010100 &
#119
0#
#120
1#
b1111111111010011 &
#121
0#
#122
1#
b1111111111010010 &
#123
0#
#124
1#
b1111111111010001 &
#125
0#
#126
1#
b1111111111010000 &
#127
0#
#128
1#
b1111111111001111 &
#129
0#
#130
1#
b1111111111001110 &
#131
0#
#132
1#
b1111111111001101 &
#133
0#
#134
1#
b1111111111001100 &
#135
0#
#136
1#
b1111111111001011 &
#137
0#
#138
1#
b1111111111001010 &
#139
0#
#140
1#
b1111111111001001 &
#141
0#
#142
1#
b1111111111001000 &
#143
0#
#144
1#
b1111111111000111 &
#145
0#
#146
1#
b1111111111000110 &
#147
0#
#148
1#
b1111111111000101 &
#149
0#
#150
1#
b1111111111000100 &
#151
0#
#152
1#
b1111111111000011 &
#153
0#
#154
1#
b1111111111000010 &
#155
0#
#156
1#
b1111111111000001 &
#157
0#
#158
1#
b1111111111000000 &
#159
0#
#160
1#
b1111111110111111 &
#161
0#
#162
1#
b1111111110111110 &
#163
0#
#164
1#
b1111111110111101 &
#165
0#
#166
1#
b1111111110111100 &
#167
0#
#168
1#
b1111111110111011 &
#169
0#
#170
1#
b1111111110111010 &
#171
0#
#172
1#
b1111111110111001 &
#173
0#
#174
1#
b1111111110111000 &
#175
0#
#176
1#
b1111111110110111 &
#177
0#
#178
1#
b1111111110110110 &
#179
0#
#180
1#
b1111111110110101 &
#181
0#
#182
1#
b1111111110110100 &
#183
0#
#184
1#
b1111111110110011 &
#185
0#
#186
1#
b1111111110110010 &
#187
0#
#188
1#
b1111111110110001 &
#189
0#
#190
1#
b1111111110110000 &
#191
0#
#192
1#
b1111111110101111 &
#193
0#
#194
1#
b1111111110101110 &
#195
0#
#196
1#
b1111111110101101 &
#197
0#
#198
1#
b1111111110101100 &
#199
0#
#200
1#
b1111111110101011 &
#201
0#
#202
1#
b1111111110101010 &
#203
0#
#204
1#
b1111111110101001 &
#205
0#
#206
1#
b1111111110101000 &
#207
0#
#208
1#
b1111111110100111 &
#209
0#
#210
1#
b1111111110100110 &
#211
0#
#212
1#
b1111111110100101 &
#213
0#
#214
1#
b1111111110100100 &
#215
0#
#216
1#
b1111111110100011 &
#217
0#
#218
1#
b1111111110100010 &
#219
0#
#220
1#
b1111111110100001 &
#221
0#
#222
1#
b1111111110100000 &
#223
0#
#224
1#
b1111111110011111 &
#225
0#
#226
1#
b1111111110011110 &
#227
0#
#228
1#
b1111111110011101 &
#229
0#
#230
1#
1%
b1111111110011100 &
#231
0#
#232
1#
b1111111110011101 &
#233
0#
#234
1#
b1111111110011110 &
#235
0#
#236
1#
b1111111110011111 &
#237
0#
#238
1#
b1111111110100000 &
#239
0#
#240
1#
b1111111110100001 &
#241
0#
#242
1#
b1111111110100010 &
#243
0#
#244
1#
b1111111110100011 &
#245
0#
#246
1#
b1111111110100100 &
#247
0#
#248
1#
b1111111110100101 &
#249
0#
#250
1#
b1111111110100110 &
#251
0#
#252
1#
b1111111110100111 &
#253
0#
#254
1#
b1111111110101000 &
#255
0#
#256
1#
b1111111110101001 &
#257
0#
#258
1#
b1111111110101010 &
#259
0#
#260
1#
b1111111110101011 &
#261
0#
#262
1#
b1111111110101100 &
#263
0#
#264
1#
b1111111110101101 &
#265
0#
#266
1#
b1111111110101110 &
#267
0#
#268
1#
b1111111110101111 &
#269
0#
#270
1#
b1111111110110000 &
#271
0#
#272
1#
b1111111110110001 &
#273
0#
#274
1#
b1111111110110010 &
#275
0#
#276
1#
b1111111110110011 &
#277
0#
#278
1#
b1111111110110100 &
#279
0#
#280
1#
b1111111110110101 &
#281
0#
#282
1#
b1111111110110110 &
#283
0#
#284
1#
b1111111110110111 &
#285
0#
#286
1#
b1111111110111000 &
#287
0#
#288
1#
b1111111110111001 &
#289
0#
#290
1#
b1111111110111010 &
#291
0#
#292
1#
b1111111110111011 &
#293
0#
#294
1#
b1111111110111100 &
#295
0#
#296
1#
b1111111110111101 &
#297
0#
#298
1#
b1111111110111110 &
#299
0#
#300
1#
0%
b1111111110111111 &
#301
0#
#302
1#
b1111111110111110 &
#303
0#
#304
1#
b1111111110111101 &
#305
0#
#306
1#
b1111111110111100 &
#307
0#
#308
1#
b1111111110111011 &
#309
0#
#310
1#
b1111111110111010 &
#311
0#
#312
1#
b1111111110111001 &
#313
0#
#314
1#
b1111111110111000 &
#315
0#
#316
1#
b1111111110110111 &
#317
0#
#318
1#
b1111111110110110 &
#319
0#
#320
1#
b1111111110110101 &
#321
0#
#322
1#
b1111111110110100 &
#323
0#
#324
1#
b1111111110110011 &
#325
0#
#326
1#
b1111111110110010 &
#327
0#
#328
1#
b1111111110110001 &
#329
0#
#330
1#
b1111111110110000 &
#331
0#
#332
1#
b1111111110101111 &
#333
0#
#334
1#
b1111111110101110 &
#335
0#
#336
1#
b1111111110101101 &
#337
0#
#338
1#
b1111111110101100 &
#339
0#
#340
1#
b1111111110101011 &
#341
0#
#342
1#
b1111111110101010 &
#343
0#
#344
1#
b1111111110101001 &
#345
0#
#346
1#
b1111111110101000 &
#347
0#
#348
1#
b1111111110100111 &
#349
0#
#350
1#
b1111111110100110 &
#351
0#
#352
1#
b1111111110100101 &
#353
0#
#354
1#
b1111111110100100 &
#355
0#
#356
1#
b1111111110100011 &
#357
0#
#358
1#
b1111111110100010 &
#359
0#
#360
1#
b1111111110100001 &
#361
0#
#362
1#
b1111111110100000 &
#363
0#
#364
1#
b1111111110011111 &
#365
0#
#366
1#
b1111111110011110 &
#367
0#
#368
1#
b1111111110011101 &
#369
0#
#370
1#
b1111111110011100 &
#371
0#
#372
1#
b1111111110011011 &
#373
0#
#374
1#
b1111111110011010 &
#375
0#
#376
1#
b1111111110011001 &
#377
0#
#378
1#
b1111111110011000 &
#379
0#
#380
1#
b1111111110010111 &
#381
0#
#382
1#
b1111111110010110 &
#383
0#
#384
1#
b1111111110010101 &
#385
0#
#386
1#
b1111111110010100 &
#387
0#
#388
1#
b1111111110010011 &
#389
0#
#390
1#
b1111111110010010 &
#391
0#
#392
1#
b1111111110010001 &
#393
0#
#394
1#
b1111111110010000 &
#395
0#
#396
1#
b1111111110001111 &
#397
0#
#398
1#
b1111111110001110 &
#399
0#
#400
1#
b1111111110001101 &
#401
0#
#402
1#
b1111111110001100 &
#403
0#
#404
1#
b1111111110001011 &
#405
0#
#406
1#
b1111111110001010 &
#407
0#
#408
1#
b1111111110001001 &
#409
0#
#410
1#
b1111111110001000 &
#411
0#
#412
1#
b1111111110000111 &
#413
0#
#414
1#
b1111111110000110 &
#415
0#
#416
1#
b1111111110000101 &
#417
0#
#418
1#
b1111111110000100 &
#419
0#
#420
1#
b1111111110000011 &
#421
0#
#422
1#
b1111111110000010 &
#423
0#
#424
1#
b1111111110000001 &
#425
0#
#426
1#
b1111111110000000 &
#427
0#
#428
1#
b1111111101111111 &
#429
0#
#430
1#
b1111111101111110 &
#431
0#
#432
1#
b1111111101111101 &
#433
0#
#434
1#
b1111111101111100 &
#435
0#
#436
1#
b1111111101111011 &
#437
0#
#438
1#
b1111111101111010 &
#439
0#
#440
1#
b1111111101111001 &
#441
0#
#442
1#
b1111111101111000 &
#443
0#
#444
1#
b1111111101110111 &
#445
0#
#446
1#
b1111111101110110 &
#447
0#
#448
1#
b1111111101110101 &
#449
0#
#450
1#
b1111111101110100 &
#451
0#
#452
1#
b1111111101110011 &
#453
0#
#454
1#
b1111111101110010 &
#455
0#
#456
1#
b1111111101110001 &
#457
0#
#458
1#
b1111111101110000 &
#459
0#
#460
1#
b1111111101101111 &
#461
0#
#462
1#
b1111111101101110 &
#463
0#
#464
1#
b1111111101101101 &
#465
0#
#466
1#
b1111111101101100 &
#467
0#
#468
1#
b1111111101101011 &
#469
0#
#470
1#
b1111111101101010 &
#471
0#
#472
1#
b1111111101101001 &
#473
0#
#474
1#
b1111111101101000 &
#475
0#
#476
1#
b1111111101100111 &
#477
0#
#478
1#
b1111111101100110 &
#479
0#
#480
1#
b1111111101100101 &
#481
0#
#482
1#
b1111111101100100 &
#483
0#
#484
1#
b1111111101100011 &
#485
0#
#486
1#
b1111111101100010 &
#487
0#
#488
1#
b1111111101100001 &
#489
0#
#490
1#
b1111111101100000 &
#491
0#
#492
1#
b1111111101011111 &
#493
0#
#494
1#
b1111111101011110 &
#495
0#
#496
1#
b1111111101011101 &
#497
0#
#498
1#
b1111111101011100 &
#499
0#
#500
1#
b1111111101011011 &
#501
0#
#502
1#
b1111111101011010 &
#503
0#
#504
1#
b1111111101011001 &
#505
0#
#506
1#
b1111111101011000 &
#507
0#
#508
1#
b1111111101010111 &
#509
0#
#510
1#
b1111111101010110 &
#511
0#
#512
1#
b1111111101010101 &
#513
0#
#514
1#
b1111111101010100 &
#515
0#
#516
1#
b1111111101010011 &
#517
0#
#518
1#
b1111111101010010 &
#519
0#
#520
1#
b1111111101010001 &
#521
0#
#522
1#
b1111111101010000 &
#523
0#
#524
1#
b1111111101001111 &
#525
0#
#526
1#
b1111111101001110 &
#527
0#
#528
1#
b1111111101001101 &
#529
0#
#530
1#
b1111111101001100 &
#531
0#
#532
1#
b1111111101001011 &
#533
0#
#534
1#
b1111111101001010 &
#535
0#
#536
1#
b1111111101001001 &
#537
0#
#538
1#
b1111111101001000 &
#539
0#
#540
1#
b1111111101000111 &
#541
0#
#542
1#
b1111111101000110 &
#543
0#
#544
1#
b1111111101000101 &
#545
0#
#546
1#
b1111111101000100 &
#547
0#
#548
1#
b1111111101000011 &
#549
0#
#550
1#
b1111111101000010 &
#551
0#
#552
1#
b1111111101000001 &
#553
0#
#554
1#
b1111111101000000 &
#555
0#
#556
1#
b1111111100111111 &
#557
0#
#558
1#
b1111111100111110 &
#559
0#
#560
1#
b1111111100111101 &
#561
0#
#562
1#
b1111111100111100 &
#563
0#
#564
1#
b1111111100111011 &
#565
0#
#566
1#
b1111111100111010 &
#567
0#
#568
1#
b1111111100111001 &
#569
0#
#570
1#
b1111111100111000 &
#571
0#
#572
1#
b1111111100110111 &
#573
0#
#574
1#
b1111111100110110 &
#575
0#
#576
1#
b1111111100110101 &
#577
0#
#578
1#
b1111111100110100 &
#579
0#
#580
1#
b1111111100110011 &
#581
0#
#582
1#
b1111111100110010 &
#583
0#
#584
1#
b1111111100110001 &
#585
0#
#586
1#
b1111111100110000 &
#587
0#
#588
1#
b1111111100101111 &
#589
0#
#590
1#
b1111111100101110 &
#591
0#
#592
1#
b1111111100101101 &
#593
0#
#594
1#
b1111111100101100 &
#595
0#
#596
1#
b1111111100101011 &
#597
0#
#598
1#
b1111111100101010 &
#599
0#
#600
1#
b1111111100101001 &
#601
0#
#602
1#
b1111111100101000 &
#603
0#
#604
1#
b1111111100100111 &
#605
0#
#606
1#
b1111111100100110 &
#607
0#
#608
1#
b1111111100100101 &
#609
0#
#610
1#
b1111111100100100 &
#611
0#
#612
1#
b1111111100100011 &
#613
0#
#614
1#
b1111111100100010 &
#615
0#
#616
1#
b1111111100100001 &
#617
0#
#618
1#
b1111111100100000 &
#619
0#
#620
1#
b1111111100011111 &
#621
0#
#622
1#
b1111111100011110 &
#623
0#
#624
1#
b1111111100011101 &
#625
0#
#626
1#
b1111111100011100 &
#627
0#
#628
1#
b1111111100011011 &
#629
0#
#630
1#
b1111111100011010 &
#631
0#
#632
1#
b1111111100011001 &
#633
0#
#634
1#
b1111111100011000 &
#635
0#
#636
1#
b1111111100010111 &
#637
0#
#638
1#
b1111111100010110 &
#639
0#
#640
1#
b1111111100010101 &
#641
0#
#642
1#
b1111111100010100 &
#643
0#
#644
1#
b1111111100010011 &
#645
0#
#646
1#
b1111111100010010 &
#647
0#
#648
1#
b1111111100010001 &
#649
0#
#650
1#
b1111111100010000 &
#651
0#
#652
1#
b1111111100001111 &
#653
0#
#654
1#
b1111111100001110 &
#655
0#
#656
1#
b1111111100001101 &
#657
0#
#658
1#
b1111111100001100 &
#659
0#
#660
1#
b1111111100001011 &
#661
0#
#662
1#
b1111111100001010 &
#663
0#
#664
1#
b1111111100001001 &
#665
0#
#666
1#
b1111111100001000 &
#667
0#
#668
1#
b1111111100000111 &
#669
0#
#670
1#
b1111111100000110 &
#671
0#
#672
1#
b1111111100000101 &
#673
0#
#674
1#
b1111111100000100 &
#675
0#
#676
1#
b1111111100000011 &
#677
0#
#678
1#
b1111111100000010 &
#679
0#
#680
1#
b1111111100000001 &
#681
0#
#682
1#
b1111111100000000 &
#683
0#
#684
1#
b1111111011111111 &
#685
0#
#686
1#
b1111111011111110 &
#687
0#
#688
1#
b1111111011111101 &
#689
0#
#690
1#
b1111111011111100 &
#691
0#
#692
1#
b1111111011111011 &
#693
0#
#694
1#
b1111111011111010 &
#695
0#
#696
1#
b1111111011111001 &
#697
0#
#698
1#
b1111111011111000 &
#699
0#
#700
1#
b1111111011110111 &
#701
0#
#702
1#
b1111111011110110 &
#703
0#
#704
1#
b1111111011110101 &
#705
0#
#706
1#
b1111111011110100 &
#707
0#
#708
1#
b1111111011110011 &
#709
0#
#710
1#
b1111111011110010 &
#711
0#
#712
1#
b1111111011110001 &
#713
0#
#714
1#
b1111111011110000 &
#715
0#
#716
1#
b1111111011101111 &
#717
0#
#718
1#
b1111111011101110 &
#719
0#
#720
1#
b1111111011101101 &
#721
0#
#722
1#
b1111111011101100 &
#723
0#
#724
1#
b1111111011101011 &
#725
0#
#726
1#
b1111111011101010 &
#727
0#
#728
1#
b1111111011101001 &
#729
0#
#730
1#
b1111111011101000 &
#731
0#
#732
1#
b1111111011100111 &
#733
0#
#734
1#
b1111111011100110 &
#735
0#
#736
1#
b1111111011100101 &
#737
0#
#738
1#
b1111111011100100 &
#739
0#
#740
1#
b1111111011100011 &
#741
0#
#742
1#
b1111111011100010 &
#743
0#
#744
1#
b1111111011100001 &
#745
0#
#746
1#
b1111111011100000 &
#747
0#
#748
1#
b1111111011011111 &
#749
0#
#750
1#
b1111111011011110 &
#751
0#
#752
1#
b1111111011011101 &
#753
0#
#754
1#
b1111111011011100 &
#755
0#
#756
1#
b1111111011011011 &
#757
0#
#758
1#
b1111111011011010 &
#759
0#
#760
1#
b1111111011011001 &
#761
0#
#762
1#
b1111111011011000 &
#763
0#
#764
1#
b1111111011010111 &
#765
0#
#766
1#
b1111111011010110 &
#767
0#
#768
1#
b1111111011010101 &
#769
0#
#770
1#
b1111111011010100 &
#771
0#
#772
1#
b1111111011010011 &
#773
0#
#774
1#
b1111111011010010 &
#775
0#
#776
1#
b1111111011010001 &
#777
0#
#778
1#
b1111111011010000 &
#779
0#
#780
1#
b1111111011001111 &
#781
0#
#782
1#
b1111111011001110 &
#783
0#
#784
1#
b1111111011001101 &
#785
0#
#786
1#
b1111111011001100 &
#787
0#
#788
1#
b1111111011001011 &
#789
0#
#790
1#
b1111111011001010 &
#791
0#
#792
1#
b1111111011001001 &
#793
0#
#794
1#
b1111111011001000 &
#795
0#
#796
1#
b1111111011000111 &
#797
0#
#798
1#
b1111111011000110 &
#799
0#
#800
1#
b1111111011000101 &
#801
0#
#802
1#
b1111111011000100 &
#803
0#
#804
1#
b1111111011000011 &
#805
0#
#806
1#
b1111111011000010 &
#807
0#
#808
1#
b1111111011000001 &
#809
0#
#810
1#
b1111111011000000 &
#811
0#
#812
1#
b1111111010111111 &
#813
0#
#814
1#
b1111111010111110 &
#815
0#
#816
1#
b1111111010111101 &
#817
0#
#818
1#
b1111111010111100 &
#819
0#
#820
1#
b1111111010111011 &
#821
0#
#822
1#
b1111111010111010 &
#823
0#
#824
1#
b1111111010111001 &
#825
0#
#826
1#
b1111111010111000 &
#827
0#
#828
1#
b1111111010110111 &
#829
0#
#830
1#
b1111111010110110 &
#831
0#
#832
1#
b1111111010110101 &
#833
0#
#834
1#
b1111111010110100 &
#835
0#
#836
1#
b1111111010110011 &
#837
0#
#838
1#
b1111111010110010 &
#839
0#
#840
1#
b1111111010110001 &
#841
0#
#842
1#
b1111111010110000 &
#843
0#
#844
1#
b1111111010101111 &
#845
0#
#846
1#
b1111111010101110 &
#847
0#
#848
1#
b1111111010101101 &
#849
0#
#850
1#
b1111111010101100 &
#851
0#
#852
1#
b1111111010101011 &
#853
0#
#854
1#
b1111111010101010 &
#855
0#
#856
1#
b1111111010101001 &
#857
0#
#858
1#
b1111111010101000 &
#859
0#
#860
1#
b1111111010100111 &
#861
0#
#862
1#
b1111111010100110 &
#863
0#
#864
1#
b1111111010100101 &
#865
0#
#866
1#
b1111111010100100 &
#867
0#
#868
1#
b1111111010100011 &
#869
0#
#870
1#
b1111111010100010 &
#871
0#
#872
1#
b1111111010100001 &
#873
0#
#874
1#
b1111111010100000 &
#875
0#
#876
1#
b1111111010011111 &
#877
0#
#878
1#
b1111111010011110 &
#879
0#
#880
1#
b1111111010011101 &
#881
0#
#882
1#
b1111111010011100 &
#883
0#
#884
1#
b1111111010011011 &
#885
0#
#886
1#
b1111111010011010 &
#887
0#
#888
1#
b1111111010011001 &
#889
0#
#890
1#
b1111111010011000 &
#891
0#
#892
1#
b1111111010010111 &
#893
0#
#894
1#
b1111111010010110 &
#895
0#
#896
1#
b1111111010010101 &
#897
0#
#898
1#
b1111111010010100 &
#899
0#
#900
1#
b1111111010010011 &
#901
0#
#902
1#
b1111111010010010 &
#903
0#
#904
1#
b1111111010010001 &
#905
0#
#906
1#
b1111111010010000 &
#907
0#
#908
1#
b1111111010001111 &
#909
0#
#910
1#
b1111111010001110 &
#911
0#
#912
1#
b1111111010001101 &
#913
0#
#914
1#
b1111111010001100 &
#915
0#
#916
1#
b1111111010001011 &
#917
0#
#918
1#
b1111111010001010 &
#919
0#
#920
1#
b1111111010001001 &
#921
0#
#922
1#
b1111111010001000 &
#923
0#
#924
1#
b1111111010000111 &
#925
0#
#926
1#
b1111111010000110 &
#927
0#
#928
1#
b1111111010000101 &
#929
0#
#930
1#
b1111111010000100 &
#931
0#
#932
1#
b1111111010000011 &
#933
0#
#934
1#
b1111111010000010 &
#935
0#
#936
1#
b1111111010000001 &
#937
0#
#938
1#
b1111111010000000 &
#939
0#
#940
1#
b1111111001111111 &
#941
0#
#942
1#
b1111111001111110 &
#943
0#
#944
1#
b1111111001111101 &
#945
0#
#946
1#
b1111111001111100 &
#947
0#
#948
1#
b1111111001111011 &
#949
0#
#950
1#
b1111111001111010 &
#951
0#
#952
1#
b1111111001111001 &
#953
0#
#954
1#
b1111111001111000 &
#955
0#
#956
1#
b1111111001110111 &
#957
0#
#958
1#
b1111111001110110 &
#959
0#
#960
1#
b1111111001110101 &
#961
0#
#962
1#
b1111111001110100 &
#963
0#
#964
1#
b1111111001110011 &
#965
0#
#966
1#
b1111111001110010 &
#967
0#
#968
1#
b1111111001110001 &
#969
0#
#970
1#
b1111111001110000 &
#971
0#
#972
1#
b1111111001101111 &
#973
0#
#974
1#
b1111111001101110 &
#975
0#
#976
1#
b1111111001101101 &
#977
0#
#978
1#
b1111111001101100 &
#979
0#
#980
1#
b1111111001101011 &
#981
0#
#982
1#
b1111111001101010 &
#983
0#
#984
1#
b1111111001101001 &
#985
0#
#986
1#
b1111111001101000 &
#987
0#
#988
1#
b1111111001100111 &
#989
0#
#990
1#
b1111111001100110 &
#991
0#
#992
1#
b1111111001100101 &
#993
0#
#994
1#
b1111111001100100 &
#995
0#
#996
1#
b1111111001100011 &
#997
0#
#998
1#
b1111111001100010 &
#999
0#
#1000
1#
b1111111001100001 &
#1001
0#
#1002
1#
b1111111001100000 &
#1003
0#
#1004
1#
b1111111001011111 &
#1005
0#
#1006
1#
b1111111001011110 &
#1007
0#
#1008
1#
b1111111001011101 &
#1009
0#
#1010
1#
b1111111001011100 &
#1011
0#
#1012
1#
b1111111001011011 &
#1013
0#
#1014
1#
b1111111001011010 &
#1015
0#
#1016
1#
b1111111001011001 &
#1017
0#
#1018
1#
b1111111001011000 &
#1019
0#
#1020
1#
b1111111001010111 &
#1021
0#
#1022
1#
b1111111001010110 &
#1023
0#
#1024
1#
b1111111001010101 &
#1025
0#
#1026
1#
b1111111001010100 &
#1027
0#
#1028
1#
b1111111001010011 &
#1029
0#
#1030
1#
b1111111001010010 &
#1031
0#
#1032
1#
b1111111001010001 &
#1033
0#
#1034
1#
b1111111001010000 &
#1035
0#
#1036
1#
b1111111001001111 &
#1037
0#
#1038
1#
b1111111001001110 &
#1039
0#
#1040
1#
b1111111001001101 &
#1041
0#
#1042
1#
b1111111001001100 &
#1043
0#
#1044
1#
b1111111001001011 &
#1045
0#
#1046
1#
b1111111001001010 &
#1047
0#
#1048
1#
b1111111001001001 &
#1049
0#
#1050
1#
b1111111001001000 &
#1051
0#
#1052
1#
b1111111001000111 &
#1053
0#
#1054
1#
b1111111001000110 &
#1055
0#
#1056
1#
b1111111001000101 &
#1057
0#
#1058
1#
b1111111001000100 &
#1059
0#
#1060
1#
b1111111001000011 &
#1061
0#
#1062
1#
b1111111001000010 &
#1063
0#
#1064
1#
b1111111001000001 &
#1065
0#
#1066
1#
b1111111001000000 &
#1067
0#
#1068
1#
b1111111000111111 &
#1069
0#
#1070
1#
b1111111000111110 &
#1071
0#
#1072
1#
b1111111000111101 &
#1073
0#
#1074
1#
b1111111000111100 &
#1075
0#
#1076
1#
b1111111000111011 &
#1077
0#
#1078
1#
b1111111000111010 &
#1079
0#
#1080
1#
b1111111000111001 &
#1081
0#
#1082
1#
b1111111000111000 &
#1083
0#
#1084
1#
b1111111000110111 &
#1085
0#
#1086
1#
b1111111000110110 &
#1087
0#
#1088
1#
b1111111000110101 &
#1089
0#
#1090
1#
b1111111000110100 &
#1091
0#
#1092
1#
b1111111000110011 &
#1093
0#
#1094
1#
b1111111000110010 &
#1095
0#
#1096
1#
b1111111000110001 &
#1097
0#
#1098
1#
b1111111000110000 &
#1099
0#
#1100
1#
b1111111000101111 &
#1101
0#
#1102
1#
b1111111000101110 &
#1103
0#
#1104
1#
b1111111000101101 &
#1105
0#
#1106
1#
b1111111000101100 &
#1107
0#
#1108
1#
b1111111000101011 &
#1109
0#
#1110
1#
b1111111000101010 &
#1111
0#
#1112
1#
b1111111000101001 &
#1113
0#
#1114
1#
b1111111000101000 &
#1115
0#
#1116
1#
b1111111000100111 &
#1117
0#
#1118
1#
b1111111000100110 &
#1119
0#
#1120
1#
b1111111000100101 &
#1121
0#
#1122
1#
b1111111000100100 &
#1123
0#
#1124
1#
b1111111000100011 &
#1125
0#
#1126
1#
b1111111000100010 &
#1127
0#
#1128
1#
b1111111000100001 &
#1129
0#
#1130
1#
b1111111000100000 &
#1131
0#
#1132
1#
b1111111000011111 &
#1133
0#
#1134
1#
b1111111000011110 &
#1135
0#
#1136
1#
b1111111000011101 &
#1137
0#
#1138
1#
b1111111000011100 &
#1139
0#
#1140
1#
b1111111000011011 &
#1141
0#
#1142
1#
b1111111000011010 &
#1143
0#
#1144
1#
b1111111000011001 &
#1145
0#
#1146
1#
b1111111000011000 &
#1147
0#
#1148
1#
b1111111000010111 &
#1149
0#
#1150
1#
b1111111000010110 &
#1151
0#
#1152
1#
b1111111000010101 &
#1153
0#
#1154
1#
b1111111000010100 &
#1155
0#
#1156
1#
b1111111000010011 &
#1157
0#
#1158
1#
b1111111000010010 &
#1159
0#
#1160
1#
b1111111000010001 &
#1161
0#
#1162
1#
b1111111000010000 &
#1163
0#
#1164
1#
b1111111000001111 &
#1165
0#
#1166
1#
b1111111000001110 &
#1167
0#
#1168
1#
b1111111000001101 &
#1169
0#
#1170
1#
b1111111000001100 &
#1171
0#
#1172
1#
b1111111000001011 &
#1173
0#
#1174
1#
b1111111000001010 &
#1175
0#
#1176
1#
b1111111000001001 &
#1177
0#
#1178
1#
b1111111000001000 &
#1179
0#
#1180
1#
b1111111000000111 &
#1181
0#
#1182
1#
b1111111000000110 &
#1183
0#
#1184
1#
b1111111000000101 &
#1185
0#
#1186
1#
b1111111000000100 &
#1187
0#
#1188
1#
b1111111000000011 &
#1189
0#
#1190
1#
b1111111000000010 &
#1191
0#
#1192
1#
b1111111000000001 &
#1193
0#
#1194
1#
b1111111000000000 &
#1195
0#
#1196
1#
b1111110111111111 &
#1197
0#
#1198
1#
b1111110111111110 &
#1199
0#
#1200
1#
b1111110111111101 &
#1201
0#
#1202
1#
b1111110111111100 &
#1203
0#
#1204
1#
b1111110111111011 &
#1205
0#
#1206
1#
b1111110111111010 &
#1207
0#
#1208
1#
b1111110111111001 &
#1209
0#
#1210
1#
b1111110111111000 &
#1211
0#
#1212
1#
b1111110111110111 &
#1213
0#
#1214
1#
b1111110111110110 &
#1215
0#
#1216
1#
b1111110111110101 &
#1217
0#
#1218
1#
b1111110111110100 &
#1219
0#
#1220
1#
b1111110111110011 &
#1221
0#
#1222
1#
b1111110111110010 &
#1223
0#
#1224
1#
b1111110111110001 &
#1225
0#
#1226
1#
b1111110111110000 &
#1227
0#
#1228
1#
b1111110111101111 &
#1229
0#
#1230
1#
b1111110111101110 &
#1231
0#
#1232
1#
b1111110111101101 &
#1233
0#
#1234
1#
b1111110111101100 &
#1235
0#
#1236
1#
b1111110111101011 &
#1237
0#
#1238
1#
b1111110111101010 &
#1239
0#
#1240
1#
b1111110111101001 &
#1241
0#
#1242
1#
b1111110111101000 &
#1243
0#
#1244
1#
b1111110111100111 &
#1245
0#
#1246
1#
b1111110111100110 &
#1247
0#
#1248
1#
b1111110111100101 &
#1249
0#
#1250
1#
b1111110111100100 &
#1251
0#
#1252
1#
b1111110111100011 &
#1253
0#
#1254
1#
b1111110111100010 &
#1255
0#
#1256
1#
b1111110111100001 &
#1257
0#
#1258
1#
b1111110111100000 &
#1259
0#
#1260
1#
b1111110111011111 &
#1261
0#
#1262
1#
b1111110111011110 &
#1263
0#
#1264
1#
b1111110111011101 &
#1265
0#
#1266
1#
b1111110111011100 &
#1267
0#
#1268
1#
b1111110111011011 &
#1269
0#
#1270
1#
b1111110111011010 &
#1271
0#
#1272
1#
b1111110111011001 &
#1273
0#
#1274
1#
b1111110111011000 &
#1275
0#
#1276
1#
b1111110111010111 &
#1277
0#
#1278
1#
b1111110111010110 &
#1279
0#
#1280
1#
b1111110111010101 &
#1281
0#
#1282
1#
b1111110111010100 &
#1283
0#
#1284
1#
b1111110111010011 &
#1285
0#
#1286
1#
b1111110111010010 &
#1287
0#
#1288
1#
b1111110111010001 &
#1289
0#
#1290
1#
b1111110111010000 &
#1291
0#
#1292
1#
b1111110111001111 &
#1293
0#
